changelog_pre_commit/__init__.py
changelog_pre_commit/main.py
changelog_pre_commit-0.1.0.dist-info/WHEEL
changelog_pre_commit-0.1.0.dist-info/METADATA
changelog_pre_commit-0.1.0.dist-info/RECORD
