Metadata-Version: 2.1
Name: changelog-pre-commit
Version: 0.1.0
Summary: 
Author: Jorge Alvarado
Author-email: alvaradosegurajorge@gmail.com
Requires-Python: >=3.8,<4.0
Classifier: Programming Language :: Python :: 3
Classifier: Programming Language :: Python :: 3.8
Classifier: Programming Language :: Python :: 3.9
Requires-Dist: GitPython (>=3.1.24,<4.0.0)
